app/.gitignore
app/__init__.py
app/config.py
app/main.py
app/models.py
app/run.py
app/routers/analysis.py
app/routers/files.py
app/services/analysis.py
app/services/analysis_types.py
app/services/cache.py
app/services/data_flow_analysis.py
app/services/focus_overlay.py
app/services/css/css_analysis.py
app/services/ipynb/ipynb_analysis.py
app/services/markdown/markdown_analysis.py
app/services/python/python_analysis.py
app/services/typescript/typescript_analysis.py
app/static/index.html
app/static/vite.svg
app/static/assets/abap-BdImnpbu.js
app/static/assets/actionscript-3-CfeIJUat.js
app/static/assets/ada-bCR0ucgS.js
app/static/assets/andromeeda-C-Jbm3Hp.js
app/static/assets/angular-html-CU67Zn6k.js
app/static/assets/angular-ts-BwZT4LLn.js
app/static/assets/apache-Pmp26Uib.js
app/static/assets/apex-DhZLUxFE.js
app/static/assets/apl-dKokRX4l.js
app/static/assets/applescript-Co6uUVPk.js
app/static/assets/ara-BRHolxvo.js
app/static/assets/asciidoc-Dv7Oe6Be.js
app/static/assets/asm-D_Q5rh1f.js
app/static/assets/astro-CbQHKStN.js
app/static/assets/aurora-x-D-2ljcwZ.js
app/static/assets/awk-DMzUqQB5.js
app/static/assets/ayu-dark-Cv9koXgw.js
app/static/assets/ballerina-BFfxhgS-.js
app/static/assets/bat-BkioyH1T.js
app/static/assets/beancount-k_qm7-4y.js
app/static/assets/berry-D08WgyRC.js
app/static/assets/bibtex-CHM0blh-.js
app/static/assets/bicep-Bmn6On1c.js
app/static/assets/blade-DVc8C-J4.js
app/static/assets/bsl-BO_Y6i37.js
app/static/assets/c-BIGW1oBm.js
app/static/assets/cadence-Bv_4Rxtq.js
app/static/assets/cairo-KRGpt6FW.js
app/static/assets/catppuccin-frappe-DFWUc33u.js
app/static/assets/catppuccin-latte-C9dUb6Cb.js
app/static/assets/catppuccin-macchiato-DQyhUUbL.js
app/static/assets/catppuccin-mocha-D87Tk5Gz.js
app/static/assets/clarity-D53aC0YG.js
app/static/assets/clojure-P80f7IUj.js
app/static/assets/cmake-D1j8_8rp.js
app/static/assets/cobol-nwyudZeR.js
app/static/assets/codeowners-Bp6g37R7.js
app/static/assets/codeql-DsOJ9woJ.js
srcly-0.1.29.dist-info/METADATA
srcly-0.1.29.dist-info/WHEEL
srcly-0.1.29.dist-info/entry_points.txt
srcly-0.1.29.dist-info/RECORD
