Metadata-Version: 2.4
Name: srcly
Version: 0.1.29
Summary: Interactive codebase treemap and metrics viewer.
Requires-Python: >=3.13
Requires-Dist: fastapi>=0.121.3
Requires-Dist: httpx>=0.28.1
Requires-Dist: lizard>=1.19.0
Requires-Dist: pathspec>=0.12.1
Requires-Dist: pydantic>=2.12.4
Requires-Dist: pytest>=9.0.1
Requires-Dist: tree-sitter-css==0.25.0
Requires-Dist: tree-sitter-markdown<0.6.0,>=0.5.1
Requires-Dist: tree-sitter-python==0.25.0
Requires-Dist: tree-sitter-scss==1.0.0
Requires-Dist: tree-sitter-typescript>=0.23.2
Requires-Dist: tree-sitter>=0.25.2
Requires-Dist: uvicorn>=0.38.0
